LICENSE.txt
README.md
setup.cfg
setup.py
src/MockServerLibrary/__init__.py
src/MockServerLibrary/library.py
src/MockServerLibrary/version.py
src/robotframework_mockserverlibrary.egg-info/PKG-INFO
src/robotframework_mockserverlibrary.egg-info/SOURCES.txt
src/robotframework_mockserverlibrary.egg-info/dependency_links.txt
src/robotframework_mockserverlibrary.egg-info/requires.txt
src/robotframework_mockserverlibrary.egg-info/top_level.txt