Metadata-Version: 2.1
Name: robotframework-mockserverlibrary
Version: 0.8.7.4
Summary: Robot framework library for MockServer
Home-page: https://github.com/frankvanderkuur/robotframework-mockserverlibrary
Author: Frank van der Kuur
Author-email: frank.vanderkuur@bqa.nl
Keywords: testing robotframework mockserver mock stub
License-File: LICENSE.txt
